.DS_Store
bciavm/__init__.py
bciavm/__main__.py
bciavm/core/__init__.py
bciavm/core/config.py
bciavm/data/__init__.py
bciavm/data/dfPricesEpc_parquet/__init__.py
bciavm/data/lookup_table_parquet/__init__.py
bciavm/exceptions/__init__.py
bciavm/exceptions/exceptions.py
bciavm/model_family/__init__.py
bciavm/model_family/model_family.py
bciavm/model_family/utils.py
bciavm/objectives/__init__.py
bciavm/objectives/binary_classification_objective.py
bciavm/objectives/fraud_cost.py
bciavm/objectives/lead_scoring.py
bciavm/objectives/multiclass_classification_objective.py
bciavm/objectives/objective_base.py
bciavm/objectives/regression_objective.py
bciavm/objectives/standard_metrics.py
bciavm/objectives/time_series_regression_objective.py
bciavm/objectives/utils.py
bciavm/pipelines/__init__.py
bciavm/pipelines/component_graph.py
bciavm/pipelines/dask_wrapper.py
bciavm/pipelines/pipeline_base.py
bciavm/pipelines/pipeline_meta.py
bciavm/pipelines/regression_pipeline.py
bciavm/pipelines/time_series_baselines.py
bciavm/pipelines/time_series_regression_pipeline.py
bciavm/pipelines/utils.py
bciavm/pipelines/components/__init__.py
bciavm/pipelines/components/component_base.py
bciavm/pipelines/components/component_base_meta.py
bciavm/pipelines/components/utils.py
bciavm/pipelines/components/ensemble/__init__.py
bciavm/pipelines/components/ensemble/stacked_ensemble_base.py
bciavm/pipelines/components/ensemble/stacked_ensemble_regressor.py
bciavm/pipelines/components/estimators/__init__.py
bciavm/pipelines/components/estimators/estimator.py
bciavm/pipelines/components/estimators/regressors/__init__.py
bciavm/pipelines/components/estimators/regressors/linear_regressor.py
bciavm/pipelines/components/estimators/regressors/neighbors.py
bciavm/pipelines/components/estimators/regressors/neural_network.py
bciavm/pipelines/components/estimators/regressors/xgboost_regressor.py
bciavm/pipelines/components/transformers/__init__.py
bciavm/pipelines/components/transformers/column_selectors.py
bciavm-1.21.26.dist-info/LICENSE
bciavm-1.21.26.dist-info/METADATA
bciavm-1.21.26.dist-info/WHEEL
bciavm-1.21.26.dist-info/entry_points.txt
bciavm-1.21.26.dist-info/top_level.txt
bciavm-1.21.26.dist-info/RECORD
