Metadata-Version: 2.1
Name: bciavm
Version: 1.21.26
Summary: bciAVM is a machine learning pipeline used to predict property prices.
Home-page: https://github.com/BlockchainClimateInstitute/microservice_price
Author: Mike Casale | Blockchain Climate Institute
Author-email: mike.casale@blockchainclimate.org
License: UNKNOWN
Download-URL: https://github.com/BlockchainClimateInstitute/microservice_price/archive/bciavm-1.21.26.tar.gz
Platform: UNKNOWN
Requires-Dist: numpy
Requires-Dist: google-auth (<2.0dev)
Requires-Dist: dask
Requires-Dist: dask-ml
Requires-Dist: docker (<5.0.0)
Requires-Dist: pandas
Requires-Dist: elasticsearch (==7.12.0)
Requires-Dist: elasticsearch-dsl
Requires-Dist: scipy
Requires-Dist: scikit-learn
Requires-Dist: scikit-optimize
Requires-Dist: pyzmq (<22.0.0)
Requires-Dist: colorama
Requires-Dist: cloudpickle (==1.6.0)
Requires-Dist: click (>=7.0.0)
Requires-Dist: psutil (>=5.6.3)
Requires-Dist: requirements-parser (>=0.2.0)
Requires-Dist: texttable (>=1.6.2)
Requires-Dist: woodwork (==0.1.0)
Requires-Dist: featuretools (>=0.20.0)
Requires-Dist: nlp-primitives (>=1.1.0)
Requires-Dist: networkx (>=2.5)
Requires-Dist: mlflow
Requires-Dist: mlflow[extras]
Requires-Dist: hyperopt
Requires-Dist: jupyter
Requires-Dist: plotly (>=4.14.0)
Requires-Dist: kaleido (>=0.1.0)
Requires-Dist: ipywidgets (>=7.5)
Requires-Dist: xgboost (<1.3.0,>=0.82)
Requires-Dist: matplotlib (>=3.3.3)
Requires-Dist: graphviz (>=0.13)
Requires-Dist: seaborn (>=0.11.1)
Requires-Dist: category-encoders (>=2.0.0)
Requires-Dist: statsmodels (>=0.12.2)
Requires-Dist: starlette
Requires-Dist: python-dotenv
Requires-Dist: hyperopt (==0.2.5)
Requires-Dist: dask (==2021.06.2)
Requires-Dist: distributed (==2021.06.2)
Requires-Dist: sktime (>=0.5.3) ; python_version < "3.9"
